{
  "col": {
    "background": {
      "default": {
        "value": "white",
        "type": "color",
        "filePath": "/Users/victorneves/_code/EKP-Frontend/styleDictionary/tokens/enbw/color/background.json",
        "isSource": true,
        "original": {
          "value": "{col.base.white.value}",
          "type": "color"
        },
        "name": "col-background-default",
        "attributes": {},
        "path": [
          "col",
          "background",
          "default"
        ]
      },
      "main": {
        "value": "#F5F5F5",
        "type": "color",
        "filePath": "/Users/victorneves/_code/EKP-Frontend/styleDictionary/tokens/enbw/color/background.json",
        "isSource": true,
        "original": {
          "value": "{col.base.neutralgrey.10.value}",
          "type": "color"
        },
        "name": "col-background-main",
        "attributes": {},
        "path": [
          "col",
          "background",
          "main"
        ]
      },
      "dark": {
        "value": "black",
        "type": "color",
        "filePath": "/Users/victorneves/_code/EKP-Frontend/styleDictionary/tokens/enbw/color/background.json",
        "isSource": true,
        "original": {
          "value": "{col.base.black.value}",
          "type": "color"
        },
        "name": "col-background-dark",
        "attributes": {},
        "path": [
          "col",
          "background",
          "dark"
        ]
      },
      "emphasized": {
        "value": "#FFEBA6 ",
        "type": "color",
        "filePath": "/Users/victorneves/_code/EKP-Frontend/styleDictionary/tokens/enbw/color/background.json",
        "isSource": true,
        "original": {
          "value": "{col.base.sunnyellow.20.value}",
          "type": "color"
        },
        "name": "col-background-emphasized",
        "attributes": {},
        "path": [
          "col",
          "background",
          "emphasized"
        ]
      },
      "brand": {
        "value": "#000099",
        "type": "color",
        "filePath": "/Users/victorneves/_code/EKP-Frontend/styleDictionary/tokens/enbw/color/background.json",
        "isSource": true,
        "original": {
          "value": "{col.brand.value}",
          "type": "color"
        },
        "name": "col-background-brand",
        "attributes": {},
        "path": [
          "col",
          "background",
          "brand"
        ]
      },
      "button": {
        "default": {
          "value": "#000099",
          "type": "color",
          "filePath": "/Users/victorneves/_code/EKP-Frontend/styleDictionary/tokens/enbw/color/background.json",
          "isSource": true,
          "original": {
            "value": "{col.brand.value}",
            "type": "color"
          },
          "name": "col-background-button-default",
          "attributes": {},
          "path": [
            "col",
            "background",
            "button",
            "default"
          ]
        },
        "active": {
          "value": "#000099",
          "type": "color",
          "filePath": "/Users/victorneves/_code/EKP-Frontend/styleDictionary/tokens/enbw/color/background.json",
          "isSource": true,
          "original": {
            "value": "{col.brand.value}",
            "type": "color"
          },
          "name": "col-background-button-active",
          "attributes": {},
          "path": [
            "col",
            "background",
            "button",
            "active"
          ]
        },
        "disabled": {
          "value": "#000099",
          "type": "color",
          "filePath": "/Users/victorneves/_code/EKP-Frontend/styleDictionary/tokens/enbw/color/background.json",
          "isSource": true,
          "original": {
            "value": "{col.brand.value}",
            "type": "color"
          },
          "name": "col-background-button-disabled",
          "attributes": {},
          "path": [
            "col",
            "background",
            "button",
            "disabled"
          ]
        }
      },
      "alert": {
        "value": "#FFDE80",
        "type": "color",
        "filePath": "/Users/victorneves/_code/EKP-Frontend/styleDictionary/tokens/enbw/color/background.json",
        "isSource": true,
        "original": {
          "value": "{col.base.sunnyellow.30.value}",
          "type": "color"
        },
        "name": "col-background-alert",
        "attributes": {},
        "path": [
          "col",
          "background",
          "alert"
        ]
      },
      "warn": {
        "value": "#FF9E82",
        "type": "color",
        "filePath": "/Users/victorneves/_code/EKP-Frontend/styleDictionary/tokens/enbw/color/background.json",
        "isSource": true,
        "original": {
          "value": "{col.base.tarocco.30.value}",
          "type": "color"
        },
        "name": "col-background-warn",
        "attributes": {},
        "path": [
          "col",
          "background",
          "warn"
        ]
      },
      "success": {
        "value": "#BADE8F",
        "type": "color",
        "filePath": "/Users/victorneves/_code/EKP-Frontend/styleDictionary/tokens/enbw/color/background.json",
        "isSource": true,
        "original": {
          "value": "{col.base.lindgreen.30.value}",
          "type": "color"
        },
        "name": "col-background-success",
        "attributes": {},
        "path": [
          "col",
          "background",
          "success"
        ]
      }
    },
    "base": {
      "azur": {
        "10": {
          "value": "#BDE5FF",
          "type": "color",
          "filePath": "/Users/victorneves/_code/EKP-Frontend/styleDictionary/tokens/enbw/color/base.json",
          "isSource": true,
          "original": {
            "value": "#BDE5FF",
            "type": "color"
          },
          "name": "col-base-azur-10",
          "attributes": {},
          "path": [
            "col",
            "base",
            "azur",
            "10"
          ]
        },
        "20": {
          "value": "#91D4FF",
          "type": "color",
          "filePath": "/Users/victorneves/_code/EKP-Frontend/styleDictionary/tokens/enbw/color/base.json",
          "isSource": true,
          "original": {
            "value": "#91D4FF",
            "type": "color"
          },
          "name": "col-base-azur-20",
          "attributes": {},
          "path": [
            "col",
            "base",
            "azur",
            "20"
          ]
        },
        "30": {
          "value": "#69C2FF",
          "type": "color",
          "filePath": "/Users/victorneves/_code/EKP-Frontend/styleDictionary/tokens/enbw/color/base.json",
          "isSource": true,
          "original": {
            "value": "#69C2FF",
            "type": "color"
          },
          "name": "col-base-azur-30",
          "attributes": {},
          "path": [
            "col",
            "base",
            "azur",
            "30"
          ]
        },
        "40": {
          "value": "#40ABF2 ",
          "type": "color",
          "filePath": "/Users/victorneves/_code/EKP-Frontend/styleDictionary/tokens/enbw/color/base.json",
          "isSource": true,
          "original": {
            "value": "#40ABF2 ",
            "type": "color"
          },
          "name": "col-base-azur-40",
          "attributes": {},
          "path": [
            "col",
            "base",
            "azur",
            "40"
          ]
        },
        "50": {
          "value": "#1796EB",
          "type": "color",
          "filePath": "/Users/victorneves/_code/EKP-Frontend/styleDictionary/tokens/enbw/color/base.json",
          "isSource": true,
          "original": {
            "value": "#1796EB",
            "type": "color"
          },
          "name": "col-base-azur-50",
          "attributes": {},
          "path": [
            "col",
            "base",
            "azur",
            "50"
          ]
        },
        "60": {
          "value": "#0878D4",
          "type": "color",
          "filePath": "/Users/victorneves/_code/EKP-Frontend/styleDictionary/tokens/enbw/color/base.json",
          "isSource": true,
          "original": {
            "value": "#0878D4",
            "type": "color"
          },
          "name": "col-base-azur-60",
          "attributes": {},
          "path": [
            "col",
            "base",
            "azur",
            "60"
          ]
        },
        "70": {
          "value": "#0A58B8 ",
          "type": "color",
          "filePath": "/Users/victorneves/_code/EKP-Frontend/styleDictionary/tokens/enbw/color/base.json",
          "isSource": true,
          "original": {
            "value": "#0A58B8 ",
            "type": "color"
          },
          "name": "col-base-azur-70",
          "attributes": {},
          "path": [
            "col",
            "base",
            "azur",
            "70"
          ]
        },
        "80": {
          "value": "#05338F",
          "type": "color",
          "filePath": "/Users/victorneves/_code/EKP-Frontend/styleDictionary/tokens/enbw/color/base.json",
          "isSource": true,
          "original": {
            "value": "#05338F",
            "type": "color"
          },
          "name": "col-base-azur-80",
          "attributes": {},
          "path": [
            "col",
            "base",
            "azur",
            "80"
          ]
        },
        "90": {
          "value": "#00175C",
          "type": "color",
          "filePath": "/Users/victorneves/_code/EKP-Frontend/styleDictionary/tokens/enbw/color/base.json",
          "isSource": true,
          "original": {
            "value": "#00175C",
            "type": "color"
          },
          "name": "col-base-azur-90",
          "attributes": {},
          "path": [
            "col",
            "base",
            "azur",
            "90"
          ]
        },
        "100": {
          "value": "#000240",
          "type": "color",
          "filePath": "/Users/victorneves/_code/EKP-Frontend/styleDictionary/tokens/enbw/color/base.json",
          "isSource": true,
          "original": {
            "value": "#000240",
            "type": "color"
          },
          "name": "col-base-azur-100",
          "attributes": {},
          "path": [
            "col",
            "base",
            "azur",
            "100"
          ]
        },
        "00": {
          "value": "#DBF1FF",
          "type": "color",
          "filePath": "/Users/victorneves/_code/EKP-Frontend/styleDictionary/tokens/enbw/color/base.json",
          "isSource": true,
          "original": {
            "value": "#DBF1FF",
            "type": "color"
          },
          "name": "col-base-azur-00",
          "attributes": {},
          "path": [
            "col",
            "base",
            "azur",
            "00"
          ]
        }
      },
      "lindgreen": {
        "10": {
          "value": "#E6F7D2",
          "type": "color",
          "filePath": "/Users/victorneves/_code/EKP-Frontend/styleDictionary/tokens/enbw/color/base.json",
          "isSource": true,
          "original": {
            "value": "#E6F7D2",
            "type": "color"
          },
          "name": "col-base-lindgreen-10",
          "attributes": {},
          "path": [
            "col",
            "base",
            "lindgreen",
            "10"
          ]
        },
        "20": {
          "value": "#D6F0B5",
          "type": "color",
          "filePath": "/Users/victorneves/_code/EKP-Frontend/styleDictionary/tokens/enbw/color/base.json",
          "isSource": true,
          "original": {
            "value": "#D6F0B5",
            "type": "color"
          },
          "name": "col-base-lindgreen-20",
          "attributes": {},
          "path": [
            "col",
            "base",
            "lindgreen",
            "20"
          ]
        },
        "30": {
          "value": "#BADE8F",
          "type": "color",
          "filePath": "/Users/victorneves/_code/EKP-Frontend/styleDictionary/tokens/enbw/color/base.json",
          "isSource": true,
          "original": {
            "value": "#BADE8F",
            "type": "color"
          },
          "name": "col-base-lindgreen-30",
          "attributes": {},
          "path": [
            "col",
            "base",
            "lindgreen",
            "30"
          ]
        },
        "40": {
          "value": "#A1CF6B",
          "type": "color",
          "filePath": "/Users/victorneves/_code/EKP-Frontend/styleDictionary/tokens/enbw/color/base.json",
          "isSource": true,
          "original": {
            "value": "#A1CF6B",
            "type": "color"
          },
          "name": "col-base-lindgreen-40",
          "attributes": {},
          "path": [
            "col",
            "base",
            "lindgreen",
            "40"
          ]
        },
        "50": {
          "value": "#87C242",
          "type": "color",
          "filePath": "/Users/victorneves/_code/EKP-Frontend/styleDictionary/tokens/enbw/color/base.json",
          "isSource": true,
          "original": {
            "value": "#87C242",
            "type": "color"
          },
          "name": "col-base-lindgreen-50",
          "attributes": {},
          "path": [
            "col",
            "base",
            "lindgreen",
            "50"
          ]
        },
        "60": {
          "value": "#72A636",
          "type": "color",
          "filePath": "/Users/victorneves/_code/EKP-Frontend/styleDictionary/tokens/enbw/color/base.json",
          "isSource": true,
          "original": {
            "value": "#72A636",
            "type": "color"
          },
          "name": "col-base-lindgreen-60",
          "attributes": {},
          "path": [
            "col",
            "base",
            "lindgreen",
            "60"
          ]
        },
        "70": {
          "value": "#548226",
          "type": "color",
          "filePath": "/Users/victorneves/_code/EKP-Frontend/styleDictionary/tokens/enbw/color/base.json",
          "isSource": true,
          "original": {
            "value": "#548226",
            "type": "color"
          },
          "name": "col-base-lindgreen-70",
          "attributes": {},
          "path": [
            "col",
            "base",
            "lindgreen",
            "70"
          ]
        },
        "80": {
          "value": "#3C6313 ",
          "type": "color",
          "filePath": "/Users/victorneves/_code/EKP-Frontend/styleDictionary/tokens/enbw/color/base.json",
          "isSource": true,
          "original": {
            "value": "#3C6313 ",
            "type": "color"
          },
          "name": "col-base-lindgreen-80",
          "attributes": {},
          "path": [
            "col",
            "base",
            "lindgreen",
            "80"
          ]
        },
        "90": {
          "value": "#26410C",
          "type": "color",
          "filePath": "/Users/victorneves/_code/EKP-Frontend/styleDictionary/tokens/enbw/color/base.json",
          "isSource": true,
          "original": {
            "value": "#26410C",
            "type": "color"
          },
          "name": "col-base-lindgreen-90",
          "attributes": {},
          "path": [
            "col",
            "base",
            "lindgreen",
            "90"
          ]
        },
        "100": {
          "value": "#102702 ",
          "type": "color",
          "filePath": "/Users/victorneves/_code/EKP-Frontend/styleDictionary/tokens/enbw/color/base.json",
          "isSource": true,
          "original": {
            "value": "#102702 ",
            "type": "color"
          },
          "name": "col-base-lindgreen-100",
          "attributes": {},
          "path": [
            "col",
            "base",
            "lindgreen",
            "100"
          ]
        },
        "00": {
          "value": "#F1FAE5",
          "type": "color",
          "filePath": "/Users/victorneves/_code/EKP-Frontend/styleDictionary/tokens/enbw/color/base.json",
          "isSource": true,
          "original": {
            "value": "#F1FAE5",
            "type": "color"
          },
          "name": "col-base-lindgreen-00",
          "attributes": {},
          "path": [
            "col",
            "base",
            "lindgreen",
            "00"
          ]
        }
      },
      "aquamarin": {
        "10": {
          "value": "#D9FFFA",
          "type": "color",
          "filePath": "/Users/victorneves/_code/EKP-Frontend/styleDictionary/tokens/enbw/color/base.json",
          "isSource": true,
          "original": {
            "value": "#D9FFFA",
            "type": "color"
          },
          "name": "col-base-aquamarin-10",
          "attributes": {},
          "path": [
            "col",
            "base",
            "aquamarin",
            "10"
          ]
        },
        "20": {
          "value": "#BAFFF7",
          "type": "color",
          "filePath": "/Users/victorneves/_code/EKP-Frontend/styleDictionary/tokens/enbw/color/base.json",
          "isSource": true,
          "original": {
            "value": "#BAFFF7",
            "type": "color"
          },
          "name": "col-base-aquamarin-20",
          "attributes": {},
          "path": [
            "col",
            "base",
            "aquamarin",
            "20"
          ]
        },
        "30": {
          "value": "#8CFAED",
          "type": "color",
          "filePath": "/Users/victorneves/_code/EKP-Frontend/styleDictionary/tokens/enbw/color/base.json",
          "isSource": true,
          "original": {
            "value": "#8CFAED",
            "type": "color"
          },
          "name": "col-base-aquamarin-30",
          "attributes": {},
          "path": [
            "col",
            "base",
            "aquamarin",
            "30"
          ]
        },
        "40": {
          "value": "#70F0E0",
          "type": "color",
          "filePath": "/Users/victorneves/_code/EKP-Frontend/styleDictionary/tokens/enbw/color/base.json",
          "isSource": true,
          "original": {
            "value": "#70F0E0",
            "type": "color"
          },
          "name": "col-base-aquamarin-40",
          "attributes": {},
          "path": [
            "col",
            "base",
            "aquamarin",
            "40"
          ]
        },
        "50": {
          "value": "#5EE5D6",
          "type": "color",
          "filePath": "/Users/victorneves/_code/EKP-Frontend/styleDictionary/tokens/enbw/color/base.json",
          "isSource": true,
          "original": {
            "value": "#5EE5D6",
            "type": "color"
          },
          "name": "col-base-aquamarin-50",
          "attributes": {},
          "path": [
            "col",
            "base",
            "aquamarin",
            "50"
          ]
        },
        "60": {
          "value": "#25C6B2",
          "type": "color",
          "filePath": "/Users/victorneves/_code/EKP-Frontend/styleDictionary/tokens/enbw/color/base.json",
          "isSource": true,
          "original": {
            "value": "#25C6B2",
            "type": "color"
          },
          "name": "col-base-aquamarin-60",
          "attributes": {},
          "path": [
            "col",
            "base",
            "aquamarin",
            "60"
          ]
        },
        "70": {
          "value": "#179C8C",
          "type": "color",
          "filePath": "/Users/victorneves/_code/EKP-Frontend/styleDictionary/tokens/enbw/color/base.json",
          "isSource": true,
          "original": {
            "value": "#179C8C",
            "type": "color"
          },
          "name": "col-base-aquamarin-70",
          "attributes": {},
          "path": [
            "col",
            "base",
            "aquamarin",
            "70"
          ]
        },
        "80": {
          "value": "#0F7A6E",
          "type": "color",
          "filePath": "/Users/victorneves/_code/EKP-Frontend/styleDictionary/tokens/enbw/color/base.json",
          "isSource": true,
          "original": {
            "value": "#0F7A6E",
            "type": "color"
          },
          "name": "col-base-aquamarin-80",
          "attributes": {},
          "path": [
            "col",
            "base",
            "aquamarin",
            "80"
          ]
        },
        "90": {
          "value": "#0D5950",
          "type": "color",
          "filePath": "/Users/victorneves/_code/EKP-Frontend/styleDictionary/tokens/enbw/color/base.json",
          "isSource": true,
          "original": {
            "value": "#0D5950",
            "type": "color"
          },
          "name": "col-base-aquamarin-90",
          "attributes": {},
          "path": [
            "col",
            "base",
            "aquamarin",
            "90"
          ]
        },
        "100": {
          "value": "#0A433C",
          "type": "color",
          "filePath": "/Users/victorneves/_code/EKP-Frontend/styleDictionary/tokens/enbw/color/base.json",
          "isSource": true,
          "original": {
            "value": "#0A433C",
            "type": "color"
          },
          "name": "col-base-aquamarin-100",
          "attributes": {},
          "path": [
            "col",
            "base",
            "aquamarin",
            "100"
          ]
        },
        "00": {
          "value": "#EBFFFC",
          "type": "color",
          "filePath": "/Users/victorneves/_code/EKP-Frontend/styleDictionary/tokens/enbw/color/base.json",
          "isSource": true,
          "original": {
            "value": "#EBFFFC",
            "type": "color"
          },
          "name": "col-base-aquamarin-00",
          "attributes": {},
          "path": [
            "col",
            "base",
            "aquamarin",
            "00"
          ]
        }
      },
      "sunnyellow": {
        "10": {
          "value": "#FFF0BD",
          "type": "color",
          "filePath": "/Users/victorneves/_code/EKP-Frontend/styleDictionary/tokens/enbw/color/base.json",
          "isSource": true,
          "original": {
            "value": "#FFF0BD",
            "type": "color"
          },
          "name": "col-base-sunnyellow-10",
          "attributes": {},
          "path": [
            "col",
            "base",
            "sunnyellow",
            "10"
          ]
        },
        "20": {
          "value": "#FFEBA6 ",
          "type": "color",
          "filePath": "/Users/victorneves/_code/EKP-Frontend/styleDictionary/tokens/enbw/color/base.json",
          "isSource": true,
          "original": {
            "value": "#FFEBA6 ",
            "type": "color"
          },
          "name": "col-base-sunnyellow-20",
          "attributes": {},
          "path": [
            "col",
            "base",
            "sunnyellow",
            "20"
          ]
        },
        "30": {
          "value": "#FFDE80",
          "type": "color",
          "filePath": "/Users/victorneves/_code/EKP-Frontend/styleDictionary/tokens/enbw/color/base.json",
          "isSource": true,
          "original": {
            "value": "#FFDE80",
            "type": "color"
          },
          "name": "col-base-sunnyellow-30",
          "attributes": {},
          "path": [
            "col",
            "base",
            "sunnyellow",
            "30"
          ]
        },
        "40": {
          "value": "#FFD45E",
          "type": "color",
          "filePath": "/Users/victorneves/_code/EKP-Frontend/styleDictionary/tokens/enbw/color/base.json",
          "isSource": true,
          "original": {
            "value": "#FFD45E",
            "type": "color"
          },
          "name": "col-base-sunnyellow-40",
          "attributes": {},
          "path": [
            "col",
            "base",
            "sunnyellow",
            "40"
          ]
        },
        "50": {
          "value": "#FFC736",
          "type": "color",
          "filePath": "/Users/victorneves/_code/EKP-Frontend/styleDictionary/tokens/enbw/color/base.json",
          "isSource": true,
          "original": {
            "value": "#FFC736",
            "type": "color"
          },
          "name": "col-base-sunnyellow-50",
          "attributes": {},
          "path": [
            "col",
            "base",
            "sunnyellow",
            "50"
          ]
        },
        "60": {
          "value": "#F0B000",
          "type": "color",
          "filePath": "/Users/victorneves/_code/EKP-Frontend/styleDictionary/tokens/enbw/color/base.json",
          "isSource": true,
          "original": {
            "value": "#F0B000",
            "type": "color"
          },
          "name": "col-base-sunnyellow-60",
          "attributes": {},
          "path": [
            "col",
            "base",
            "sunnyellow",
            "60"
          ]
        },
        "70": {
          "value": "#CC8B00",
          "type": "color",
          "filePath": "/Users/victorneves/_code/EKP-Frontend/styleDictionary/tokens/enbw/color/base.json",
          "isSource": true,
          "original": {
            "value": "#CC8B00",
            "type": "color"
          },
          "name": "col-base-sunnyellow-70",
          "attributes": {},
          "path": [
            "col",
            "base",
            "sunnyellow",
            "70"
          ]
        },
        "80": {
          "value": "#A06703",
          "type": "color",
          "filePath": "/Users/victorneves/_code/EKP-Frontend/styleDictionary/tokens/enbw/color/base.json",
          "isSource": true,
          "original": {
            "value": "#A06703",
            "type": "color"
          },
          "name": "col-base-sunnyellow-80",
          "attributes": {},
          "path": [
            "col",
            "base",
            "sunnyellow",
            "80"
          ]
        },
        "90": {
          "value": "#804A00",
          "type": "color",
          "filePath": "/Users/victorneves/_code/EKP-Frontend/styleDictionary/tokens/enbw/color/base.json",
          "isSource": true,
          "original": {
            "value": "#804A00",
            "type": "color"
          },
          "name": "col-base-sunnyellow-90",
          "attributes": {},
          "path": [
            "col",
            "base",
            "sunnyellow",
            "90"
          ]
        },
        "100": {
          "value": "#573300",
          "type": "color",
          "filePath": "/Users/victorneves/_code/EKP-Frontend/styleDictionary/tokens/enbw/color/base.json",
          "isSource": true,
          "original": {
            "value": "#573300",
            "type": "color"
          },
          "name": "col-base-sunnyellow-100",
          "attributes": {},
          "path": [
            "col",
            "base",
            "sunnyellow",
            "100"
          ]
        },
        "00": {
          "value": "#FFF9E5",
          "type": "color",
          "filePath": "/Users/victorneves/_code/EKP-Frontend/styleDictionary/tokens/enbw/color/base.json",
          "isSource": true,
          "original": {
            "value": "#FFF9E5",
            "type": "color"
          },
          "name": "col-base-sunnyellow-00",
          "attributes": {},
          "path": [
            "col",
            "base",
            "sunnyellow",
            "00"
          ]
        }
      },
      "greybeige": {
        "10": {
          "value": "#FFF5EB",
          "type": "color",
          "filePath": "/Users/victorneves/_code/EKP-Frontend/styleDictionary/tokens/enbw/color/base.json",
          "isSource": true,
          "original": {
            "value": "#FFF5EB",
            "type": "color"
          },
          "name": "col-base-greybeige-10",
          "attributes": {},
          "path": [
            "col",
            "base",
            "greybeige",
            "10"
          ]
        },
        "20": {
          "value": "#F7E8D1",
          "type": "color",
          "filePath": "/Users/victorneves/_code/EKP-Frontend/styleDictionary/tokens/enbw/color/base.json",
          "isSource": true,
          "original": {
            "value": "#F7E8D1",
            "type": "color"
          },
          "name": "col-base-greybeige-20",
          "attributes": {},
          "path": [
            "col",
            "base",
            "greybeige",
            "20"
          ]
        },
        "30": {
          "value": "#F5DEC2",
          "type": "color",
          "filePath": "/Users/victorneves/_code/EKP-Frontend/styleDictionary/tokens/enbw/color/base.json",
          "isSource": true,
          "original": {
            "value": "#F5DEC2",
            "type": "color"
          },
          "name": "col-base-greybeige-30",
          "attributes": {},
          "path": [
            "col",
            "base",
            "greybeige",
            "30"
          ]
        },
        "40": {
          "value": "#EBCFAD",
          "type": "color",
          "filePath": "/Users/victorneves/_code/EKP-Frontend/styleDictionary/tokens/enbw/color/base.json",
          "isSource": true,
          "original": {
            "value": "#EBCFAD",
            "type": "color"
          },
          "name": "col-base-greybeige-40",
          "attributes": {},
          "path": [
            "col",
            "base",
            "greybeige",
            "40"
          ]
        },
        "50": {
          "value": "#E3C299",
          "type": "color",
          "filePath": "/Users/victorneves/_code/EKP-Frontend/styleDictionary/tokens/enbw/color/base.json",
          "isSource": true,
          "original": {
            "value": "#E3C299",
            "type": "color"
          },
          "name": "col-base-greybeige-50",
          "attributes": {},
          "path": [
            "col",
            "base",
            "greybeige",
            "50"
          ]
        },
        "60": {
          "value": "#CBA676",
          "type": "color",
          "filePath": "/Users/victorneves/_code/EKP-Frontend/styleDictionary/tokens/enbw/color/base.json",
          "isSource": true,
          "original": {
            "value": "#CBA676",
            "type": "color"
          },
          "name": "col-base-greybeige-60",
          "attributes": {},
          "path": [
            "col",
            "base",
            "greybeige",
            "60"
          ]
        },
        "70": {
          "value": "#AD8552",
          "type": "color",
          "filePath": "/Users/victorneves/_code/EKP-Frontend/styleDictionary/tokens/enbw/color/base.json",
          "isSource": true,
          "original": {
            "value": "#AD8552",
            "type": "color"
          },
          "name": "col-base-greybeige-70",
          "attributes": {},
          "path": [
            "col",
            "base",
            "greybeige",
            "70"
          ]
        },
        "80": {
          "value": "#846239",
          "type": "color",
          "filePath": "/Users/victorneves/_code/EKP-Frontend/styleDictionary/tokens/enbw/color/base.json",
          "isSource": true,
          "original": {
            "value": "#846239",
            "type": "color"
          },
          "name": "col-base-greybeige-80",
          "attributes": {},
          "path": [
            "col",
            "base",
            "greybeige",
            "80"
          ]
        },
        "90": {
          "value": "#614524",
          "type": "color",
          "filePath": "/Users/victorneves/_code/EKP-Frontend/styleDictionary/tokens/enbw/color/base.json",
          "isSource": true,
          "original": {
            "value": "#614524",
            "type": "color"
          },
          "name": "col-base-greybeige-90",
          "attributes": {},
          "path": [
            "col",
            "base",
            "greybeige",
            "90"
          ]
        },
        "100": {
          "value": "#493113",
          "type": "color",
          "filePath": "/Users/victorneves/_code/EKP-Frontend/styleDictionary/tokens/enbw/color/base.json",
          "isSource": true,
          "original": {
            "value": "#493113",
            "type": "color"
          },
          "name": "col-base-greybeige-100",
          "attributes": {},
          "path": [
            "col",
            "base",
            "greybeige",
            "100"
          ]
        },
        "00": {
          "value": "#FEFAF5",
          "type": "color",
          "filePath": "/Users/victorneves/_code/EKP-Frontend/styleDictionary/tokens/enbw/color/base.json",
          "isSource": true,
          "original": {
            "value": "#FEFAF5",
            "type": "color"
          },
          "name": "col-base-greybeige-00",
          "attributes": {},
          "path": [
            "col",
            "base",
            "greybeige",
            "00"
          ]
        }
      },
      "tarocco": {
        "10": {
          "value": "#FFDED4",
          "type": "color",
          "filePath": "/Users/victorneves/_code/EKP-Frontend/styleDictionary/tokens/enbw/color/base.json",
          "isSource": true,
          "original": {
            "value": "#FFDED4",
            "type": "color"
          },
          "name": "col-base-tarocco-10",
          "attributes": {},
          "path": [
            "col",
            "base",
            "tarocco",
            "10"
          ]
        },
        "20": {
          "value": "#FFC2B0",
          "type": "color",
          "filePath": "/Users/victorneves/_code/EKP-Frontend/styleDictionary/tokens/enbw/color/base.json",
          "isSource": true,
          "original": {
            "value": "#FFC2B0",
            "type": "color"
          },
          "name": "col-base-tarocco-20",
          "attributes": {},
          "path": [
            "col",
            "base",
            "tarocco",
            "20"
          ]
        },
        "30": {
          "value": "#FF9E82",
          "type": "color",
          "filePath": "/Users/victorneves/_code/EKP-Frontend/styleDictionary/tokens/enbw/color/base.json",
          "isSource": true,
          "original": {
            "value": "#FF9E82",
            "type": "color"
          },
          "name": "col-base-tarocco-30",
          "attributes": {},
          "path": [
            "col",
            "base",
            "tarocco",
            "30"
          ]
        },
        "40": {
          "value": "#FF7D57",
          "type": "color",
          "filePath": "/Users/victorneves/_code/EKP-Frontend/styleDictionary/tokens/enbw/color/base.json",
          "isSource": true,
          "original": {
            "value": "#FF7D57",
            "type": "color"
          },
          "name": "col-base-tarocco-40",
          "attributes": {},
          "path": [
            "col",
            "base",
            "tarocco",
            "40"
          ]
        },
        "50": {
          "value": "#FF6638",
          "type": "color",
          "filePath": "/Users/victorneves/_code/EKP-Frontend/styleDictionary/tokens/enbw/color/base.json",
          "isSource": true,
          "original": {
            "value": "#FF6638",
            "type": "color"
          },
          "name": "col-base-tarocco-50",
          "attributes": {},
          "path": [
            "col",
            "base",
            "tarocco",
            "50"
          ]
        },
        "60": {
          "value": "#E2491B",
          "type": "color",
          "filePath": "/Users/victorneves/_code/EKP-Frontend/styleDictionary/tokens/enbw/color/base.json",
          "isSource": true,
          "original": {
            "value": "#E2491B",
            "type": "color"
          },
          "name": "col-base-tarocco-60",
          "attributes": {},
          "path": [
            "col",
            "base",
            "tarocco",
            "60"
          ]
        },
        "70": {
          "value": "#C73A0F",
          "type": "color",
          "filePath": "/Users/victorneves/_code/EKP-Frontend/styleDictionary/tokens/enbw/color/base.json",
          "isSource": true,
          "original": {
            "value": "#C73A0F",
            "type": "color"
          },
          "name": "col-base-tarocco-70",
          "attributes": {},
          "path": [
            "col",
            "base",
            "tarocco",
            "70"
          ]
        },
        "80": {
          "value": "#A52D09",
          "type": "color",
          "filePath": "/Users/victorneves/_code/EKP-Frontend/styleDictionary/tokens/enbw/color/base.json",
          "isSource": true,
          "original": {
            "value": "#A52D09",
            "type": "color"
          },
          "name": "col-base-tarocco-80",
          "attributes": {},
          "path": [
            "col",
            "base",
            "tarocco",
            "80"
          ]
        },
        "90": {
          "value": "#742006",
          "type": "color",
          "filePath": "/Users/victorneves/_code/EKP-Frontend/styleDictionary/tokens/enbw/color/base.json",
          "isSource": true,
          "original": {
            "value": "#742006",
            "type": "color"
          },
          "name": "col-base-tarocco-90",
          "attributes": {},
          "path": [
            "col",
            "base",
            "tarocco",
            "90"
          ]
        },
        "100": {
          "value": "#4E1C0E",
          "type": "color",
          "filePath": "/Users/victorneves/_code/EKP-Frontend/styleDictionary/tokens/enbw/color/base.json",
          "isSource": true,
          "original": {
            "value": "#4E1C0E",
            "type": "color"
          },
          "name": "col-base-tarocco-100",
          "attributes": {},
          "path": [
            "col",
            "base",
            "tarocco",
            "100"
          ]
        },
        "00": {
          "value": "#FFF3F0",
          "type": "color",
          "filePath": "/Users/victorneves/_code/EKP-Frontend/styleDictionary/tokens/enbw/color/base.json",
          "isSource": true,
          "original": {
            "value": "#FFF3F0",
            "type": "color"
          },
          "name": "col-base-tarocco-00",
          "attributes": {},
          "path": [
            "col",
            "base",
            "tarocco",
            "00"
          ]
        }
      },
      "warmgrey": {
        "10": {
          "value": "#F7F4F3",
          "type": "color",
          "filePath": "/Users/victorneves/_code/EKP-Frontend/styleDictionary/tokens/enbw/color/base.json",
          "isSource": true,
          "original": {
            "value": "#F7F4F3",
            "type": "color"
          },
          "name": "col-base-warmgrey-10",
          "attributes": {},
          "path": [
            "col",
            "base",
            "warmgrey",
            "10"
          ]
        },
        "20": {
          "value": "#F0EEEB",
          "type": "color",
          "filePath": "/Users/victorneves/_code/EKP-Frontend/styleDictionary/tokens/enbw/color/base.json",
          "isSource": true,
          "original": {
            "value": "#F0EEEB",
            "type": "color"
          },
          "name": "col-base-warmgrey-20",
          "attributes": {},
          "path": [
            "col",
            "base",
            "warmgrey",
            "20"
          ]
        },
        "30": {
          "value": "#ECE9E4",
          "type": "color",
          "filePath": "/Users/victorneves/_code/EKP-Frontend/styleDictionary/tokens/enbw/color/base.json",
          "isSource": true,
          "original": {
            "value": "#ECE9E4",
            "type": "color"
          },
          "name": "col-base-warmgrey-30",
          "attributes": {},
          "path": [
            "col",
            "base",
            "warmgrey",
            "30"
          ]
        },
        "40": {
          "value": "#E8E3DE",
          "type": "color",
          "filePath": "/Users/victorneves/_code/EKP-Frontend/styleDictionary/tokens/enbw/color/base.json",
          "isSource": true,
          "original": {
            "value": "#E8E3DE",
            "type": "color"
          },
          "name": "col-base-warmgrey-40",
          "attributes": {},
          "path": [
            "col",
            "base",
            "warmgrey",
            "40"
          ]
        },
        "50": {
          "value": "#E5DFDA",
          "type": "color",
          "filePath": "/Users/victorneves/_code/EKP-Frontend/styleDictionary/tokens/enbw/color/base.json",
          "isSource": true,
          "original": {
            "value": "#E5DFDA",
            "type": "color"
          },
          "name": "col-base-warmgrey-50",
          "attributes": {},
          "path": [
            "col",
            "base",
            "warmgrey",
            "50"
          ]
        },
        "60": {
          "value": "#CFC9C4",
          "type": "color",
          "filePath": "/Users/victorneves/_code/EKP-Frontend/styleDictionary/tokens/enbw/color/base.json",
          "isSource": true,
          "original": {
            "value": "#CFC9C4",
            "type": "color"
          },
          "name": "col-base-warmgrey-60",
          "attributes": {},
          "path": [
            "col",
            "base",
            "warmgrey",
            "60"
          ]
        },
        "70": {
          "value": "#AAA5A1",
          "type": "color",
          "filePath": "/Users/victorneves/_code/EKP-Frontend/styleDictionary/tokens/enbw/color/base.json",
          "isSource": true,
          "original": {
            "value": "#AAA5A1",
            "type": "color"
          },
          "name": "col-base-warmgrey-70",
          "attributes": {},
          "path": [
            "col",
            "base",
            "warmgrey",
            "70"
          ]
        },
        "80": {
          "value": "#706A66",
          "type": "color",
          "filePath": "/Users/victorneves/_code/EKP-Frontend/styleDictionary/tokens/enbw/color/base.json",
          "isSource": true,
          "original": {
            "value": "#706A66",
            "type": "color"
          },
          "name": "col-base-warmgrey-80",
          "attributes": {},
          "path": [
            "col",
            "base",
            "warmgrey",
            "80"
          ]
        },
        "90": {
          "value": "#504D49",
          "type": "color",
          "filePath": "/Users/victorneves/_code/EKP-Frontend/styleDictionary/tokens/enbw/color/base.json",
          "isSource": true,
          "original": {
            "value": "#504D49",
            "type": "color"
          },
          "name": "col-base-warmgrey-90",
          "attributes": {},
          "path": [
            "col",
            "base",
            "warmgrey",
            "90"
          ]
        },
        "100": {
          "value": "#302E2C",
          "type": "color",
          "filePath": "/Users/victorneves/_code/EKP-Frontend/styleDictionary/tokens/enbw/color/base.json",
          "isSource": true,
          "original": {
            "value": "#302E2C",
            "type": "color"
          },
          "name": "col-base-warmgrey-100",
          "attributes": {},
          "path": [
            "col",
            "base",
            "warmgrey",
            "100"
          ]
        },
        "00": {
          "value": "#FBFAF9",
          "type": "color",
          "filePath": "/Users/victorneves/_code/EKP-Frontend/styleDictionary/tokens/enbw/color/base.json",
          "isSource": true,
          "original": {
            "value": "#FBFAF9",
            "type": "color"
          },
          "name": "col-base-warmgrey-00",
          "attributes": {},
          "path": [
            "col",
            "base",
            "warmgrey",
            "00"
          ]
        }
      },
      "neutralgrey": {
        "10": {
          "value": "#F5F5F5",
          "type": "color",
          "filePath": "/Users/victorneves/_code/EKP-Frontend/styleDictionary/tokens/enbw/color/base.json",
          "isSource": true,
          "original": {
            "value": "#F5F5F5",
            "type": "color"
          },
          "name": "col-base-neutralgrey-10",
          "attributes": {},
          "path": [
            "col",
            "base",
            "neutralgrey",
            "10"
          ]
        },
        "20": {
          "value": "#EDEDED",
          "type": "color",
          "filePath": "/Users/victorneves/_code/EKP-Frontend/styleDictionary/tokens/enbw/color/base.json",
          "isSource": true,
          "original": {
            "value": "#EDEDED",
            "type": "color"
          },
          "name": "col-base-neutralgrey-20",
          "attributes": {},
          "path": [
            "col",
            "base",
            "neutralgrey",
            "20"
          ]
        },
        "30": {
          "value": "#E8E8E8",
          "type": "color",
          "filePath": "/Users/victorneves/_code/EKP-Frontend/styleDictionary/tokens/enbw/color/base.json",
          "isSource": true,
          "original": {
            "value": "#E8E8E8",
            "type": "color"
          },
          "name": "col-base-neutralgrey-30",
          "attributes": {},
          "path": [
            "col",
            "base",
            "neutralgrey",
            "30"
          ]
        },
        "40": {
          "value": "#DEDEDE",
          "type": "color",
          "filePath": "/Users/victorneves/_code/EKP-Frontend/styleDictionary/tokens/enbw/color/base.json",
          "isSource": true,
          "original": {
            "value": "#DEDEDE",
            "type": "color"
          },
          "name": "col-base-neutralgrey-40",
          "attributes": {},
          "path": [
            "col",
            "base",
            "neutralgrey",
            "40"
          ]
        },
        "50": {
          "value": "#D1D1D1",
          "type": "color",
          "filePath": "/Users/victorneves/_code/EKP-Frontend/styleDictionary/tokens/enbw/color/base.json",
          "isSource": true,
          "original": {
            "value": "#D1D1D1",
            "type": "color"
          },
          "name": "col-base-neutralgrey-50",
          "attributes": {},
          "path": [
            "col",
            "base",
            "neutralgrey",
            "50"
          ]
        },
        "60": {
          "value": "#B2B2B2",
          "type": "color",
          "filePath": "/Users/victorneves/_code/EKP-Frontend/styleDictionary/tokens/enbw/color/base.json",
          "isSource": true,
          "original": {
            "value": "#B2B2B2",
            "type": "color"
          },
          "name": "col-base-neutralgrey-60",
          "attributes": {},
          "path": [
            "col",
            "base",
            "neutralgrey",
            "60"
          ]
        },
        "70": {
          "value": "#999999",
          "type": "color",
          "filePath": "/Users/victorneves/_code/EKP-Frontend/styleDictionary/tokens/enbw/color/base.json",
          "isSource": true,
          "original": {
            "value": "#999999",
            "type": "color"
          },
          "name": "col-base-neutralgrey-70",
          "attributes": {},
          "path": [
            "col",
            "base",
            "neutralgrey",
            "70"
          ]
        },
        "80": {
          "value": "#6B6B6B",
          "type": "color",
          "filePath": "/Users/victorneves/_code/EKP-Frontend/styleDictionary/tokens/enbw/color/base.json",
          "isSource": true,
          "original": {
            "value": "#6B6B6B",
            "type": "color"
          },
          "name": "col-base-neutralgrey-80",
          "attributes": {},
          "path": [
            "col",
            "base",
            "neutralgrey",
            "80"
          ]
        },
        "90": {
          "value": "#4D4D4D",
          "type": "color",
          "filePath": "/Users/victorneves/_code/EKP-Frontend/styleDictionary/tokens/enbw/color/base.json",
          "isSource": true,
          "original": {
            "value": "#4D4D4D",
            "type": "color"
          },
          "name": "col-base-neutralgrey-90",
          "attributes": {},
          "path": [
            "col",
            "base",
            "neutralgrey",
            "90"
          ]
        },
        "100": {
          "value": "#1F1F1F",
          "type": "color",
          "filePath": "/Users/victorneves/_code/EKP-Frontend/styleDictionary/tokens/enbw/color/base.json",
          "isSource": true,
          "original": {
            "value": "#1F1F1F",
            "type": "color"
          },
          "name": "col-base-neutralgrey-100",
          "attributes": {},
          "path": [
            "col",
            "base",
            "neutralgrey",
            "100"
          ]
        },
        "00": {
          "value": "#FAFAFA",
          "type": "color",
          "filePath": "/Users/victorneves/_code/EKP-Frontend/styleDictionary/tokens/enbw/color/base.json",
          "isSource": true,
          "original": {
            "value": "#FAFAFA",
            "type": "color"
          },
          "name": "col-base-neutralgrey-00",
          "attributes": {},
          "path": [
            "col",
            "base",
            "neutralgrey",
            "00"
          ]
        }
      },
      "darkblue": {
        "value": "#000099",
        "type": "color",
        "filePath": "/Users/victorneves/_code/EKP-Frontend/styleDictionary/tokens/enbw/color/base.json",
        "isSource": true,
        "original": {
          "value": "#000099",
          "type": "color"
        },
        "name": "col-base-darkblue",
        "attributes": {},
        "path": [
          "col",
          "base",
          "darkblue"
        ]
      },
      "impulseorange": {
        "value": "#FF8F0F",
        "type": "color",
        "filePath": "/Users/victorneves/_code/EKP-Frontend/styleDictionary/tokens/enbw/color/base.json",
        "isSource": true,
        "original": {
          "value": "#FF8F0F",
          "type": "color"
        },
        "name": "col-base-impulseorange",
        "attributes": {},
        "path": [
          "col",
          "base",
          "impulseorange"
        ]
      },
      "white": {
        "value": "white",
        "type": "color",
        "filePath": "/Users/victorneves/_code/EKP-Frontend/styleDictionary/tokens/enbw/color/base.json",
        "isSource": true,
        "original": {
          "value": "white",
          "type": "color"
        },
        "name": "col-base-white",
        "attributes": {},
        "path": [
          "col",
          "base",
          "white"
        ]
      },
      "black": {
        "value": "black",
        "type": "color",
        "filePath": "/Users/victorneves/_code/EKP-Frontend/styleDictionary/tokens/enbw/color/base.json",
        "isSource": true,
        "original": {
          "value": "black",
          "type": "color"
        },
        "name": "col-base-black",
        "attributes": {},
        "path": [
          "col",
          "base",
          "black"
        ]
      }
    },
    "border": {
      "default": {
        "value": "#E5DFDA",
        "type": "color",
        "filePath": "/Users/victorneves/_code/EKP-Frontend/styleDictionary/tokens/enbw/color/border.json",
        "isSource": true,
        "original": {
          "value": "{col.base.warmgrey.50.value}",
          "type": "color"
        },
        "name": "col-border-default",
        "attributes": {},
        "path": [
          "col",
          "border",
          "default"
        ]
      },
      "emphasized": {
        "value": "#FFC736",
        "type": "color",
        "filePath": "/Users/victorneves/_code/EKP-Frontend/styleDictionary/tokens/enbw/color/border.json",
        "isSource": true,
        "original": {
          "value": "{col.base.sunnyellow.50.value}",
          "type": "color"
        },
        "name": "col-border-emphasized",
        "attributes": {},
        "path": [
          "col",
          "border",
          "emphasized"
        ]
      },
      "brand": {
        "value": "#000099",
        "type": "color",
        "filePath": "/Users/victorneves/_code/EKP-Frontend/styleDictionary/tokens/enbw/color/border.json",
        "isSource": true,
        "original": {
          "value": "{col.brand.value}",
          "type": "color"
        },
        "name": "col-border-brand",
        "attributes": {},
        "path": [
          "col",
          "border",
          "brand"
        ]
      },
      "alert": {
        "value": "#FFC736",
        "type": "color",
        "filePath": "/Users/victorneves/_code/EKP-Frontend/styleDictionary/tokens/enbw/color/border.json",
        "isSource": true,
        "original": {
          "value": "{col.base.sunnyellow.50.value}",
          "type": "color"
        },
        "name": "col-border-alert",
        "attributes": {},
        "path": [
          "col",
          "border",
          "alert"
        ]
      },
      "warn": {
        "value": "#FF6638",
        "type": "color",
        "filePath": "/Users/victorneves/_code/EKP-Frontend/styleDictionary/tokens/enbw/color/border.json",
        "isSource": true,
        "original": {
          "value": "{col.base.tarocco.50.value}",
          "type": "color"
        },
        "name": "col-border-warn",
        "attributes": {},
        "path": [
          "col",
          "border",
          "warn"
        ]
      },
      "success": {
        "value": "#87C242",
        "type": "color",
        "filePath": "/Users/victorneves/_code/EKP-Frontend/styleDictionary/tokens/enbw/color/border.json",
        "isSource": true,
        "original": {
          "value": "{col.base.lindgreen.50.value}",
          "type": "color"
        },
        "name": "col-border-success",
        "attributes": {},
        "path": [
          "col",
          "border",
          "success"
        ]
      }
    },
    "brand": {
      "value": "#000099",
      "type": "color",
      "filePath": "/Users/victorneves/_code/EKP-Frontend/styleDictionary/tokens/enbw/color/brand.json",
      "isSource": true,
      "original": {
        "value": "{col.base.darkblue.value}",
        "type": "color"
      },
      "name": "col-brand",
      "attributes": {},
      "path": [
        "col",
        "brand"
      ]
    },
    "emphasized": {
      "value": "#FF8F0F",
      "type": "color",
      "filePath": "/Users/victorneves/_code/EKP-Frontend/styleDictionary/tokens/enbw/color/emphasis.json",
      "isSource": true,
      "original": {
        "value": "{col.base.impulseorange.value}",
        "type": "color"
      },
      "name": "col-emphasized",
      "attributes": {},
      "path": [
        "col",
        "emphasized"
      ]
    },
    "type": {
      "default": {
        "value": "black",
        "type": "color",
        "filePath": "/Users/victorneves/_code/EKP-Frontend/styleDictionary/tokens/enbw/color/type.json",
        "isSource": true,
        "original": {
          "value": "{col.base.black.value}",
          "type": "color"
        },
        "name": "col-type-default",
        "attributes": {},
        "path": [
          "col",
          "type",
          "default"
        ]
      },
      "inverse": {
        "value": "white",
        "type": "color",
        "filePath": "/Users/victorneves/_code/EKP-Frontend/styleDictionary/tokens/enbw/color/type.json",
        "isSource": true,
        "original": {
          "value": "{col.base.white.value}",
          "type": "color"
        },
        "name": "col-type-inverse",
        "attributes": {},
        "path": [
          "col",
          "type",
          "inverse"
        ]
      },
      "waiting": {
        "value": "#D1D1D1",
        "type": "color",
        "filePath": "/Users/victorneves/_code/EKP-Frontend/styleDictionary/tokens/enbw/color/type.json",
        "isSource": true,
        "original": {
          "value": "{col.base.neutralgrey.50.value}",
          "type": "color"
        },
        "name": "col-type-waiting",
        "attributes": {},
        "path": [
          "col",
          "type",
          "waiting"
        ]
      },
      "emphasized": {
        "value": "#FFC736",
        "type": "color",
        "filePath": "/Users/victorneves/_code/EKP-Frontend/styleDictionary/tokens/enbw/color/type.json",
        "isSource": true,
        "original": {
          "value": "{col.base.sunnyellow.50.value}",
          "type": "color"
        },
        "name": "col-type-emphasized",
        "attributes": {},
        "path": [
          "col",
          "type",
          "emphasized"
        ]
      },
      "brand": {
        "value": "#000099",
        "type": "color",
        "filePath": "/Users/victorneves/_code/EKP-Frontend/styleDictionary/tokens/enbw/color/type.json",
        "isSource": true,
        "original": {
          "value": "{col.brand.value}",
          "type": "color"
        },
        "name": "col-type-brand",
        "attributes": {},
        "path": [
          "col",
          "type",
          "brand"
        ]
      },
      "alert": {
        "value": "#FFC736",
        "type": "color",
        "filePath": "/Users/victorneves/_code/EKP-Frontend/styleDictionary/tokens/enbw/color/type.json",
        "isSource": true,
        "original": {
          "value": "{col.base.sunnyellow.50.value}",
          "type": "color"
        },
        "name": "col-type-alert",
        "attributes": {},
        "path": [
          "col",
          "type",
          "alert"
        ]
      },
      "warn": {
        "value": "#FF6638",
        "type": "color",
        "filePath": "/Users/victorneves/_code/EKP-Frontend/styleDictionary/tokens/enbw/color/type.json",
        "isSource": true,
        "original": {
          "value": "{col.base.tarocco.50.value}",
          "type": "color"
        },
        "name": "col-type-warn",
        "attributes": {},
        "path": [
          "col",
          "type",
          "warn"
        ]
      },
      "success": {
        "value": "#87C242",
        "type": "color",
        "filePath": "/Users/victorneves/_code/EKP-Frontend/styleDictionary/tokens/enbw/color/type.json",
        "isSource": true,
        "original": {
          "value": "{col.base.lindgreen.50.value}",
          "type": "color"
        },
        "name": "col-type-success",
        "attributes": {},
        "path": [
          "col",
          "type",
          "success"
        ]
      },
      "link": {
        "default": {
          "value": "#FFC736",
          "type": "color",
          "filePath": "/Users/victorneves/_code/EKP-Frontend/styleDictionary/tokens/enbw/color/type.json",
          "isSource": true,
          "original": {
            "value": "{col.base.sunnyellow.50.value}",
            "type": "color"
          },
          "name": "col-type-link-default",
          "attributes": {},
          "path": [
            "col",
            "type",
            "link",
            "default"
          ]
        },
        "hover": {
          "value": "#FFC736",
          "type": "color",
          "filePath": "/Users/victorneves/_code/EKP-Frontend/styleDictionary/tokens/enbw/color/type.json",
          "isSource": true,
          "original": {
            "value": "{col.base.sunnyellow.50.value}",
            "type": "color"
          },
          "name": "col-type-link-hover",
          "attributes": {},
          "path": [
            "col",
            "type",
            "link",
            "hover"
          ]
        },
        "active": {
          "value": "#FFC736",
          "type": "color",
          "filePath": "/Users/victorneves/_code/EKP-Frontend/styleDictionary/tokens/enbw/color/type.json",
          "isSource": true,
          "original": {
            "value": "{col.base.sunnyellow.50.value}",
            "type": "color"
          },
          "name": "col-type-link-active",
          "attributes": {},
          "path": [
            "col",
            "type",
            "link",
            "active"
          ]
        },
        "focus": {
          "value": "#FFC736",
          "type": "color",
          "filePath": "/Users/victorneves/_code/EKP-Frontend/styleDictionary/tokens/enbw/color/type.json",
          "isSource": true,
          "original": {
            "value": "{col.base.sunnyellow.50.value}",
            "type": "color"
          },
          "name": "col-type-link-focus",
          "attributes": {},
          "path": [
            "col",
            "type",
            "link",
            "focus"
          ]
        },
        "visited": {
          "value": "#FFC736",
          "type": "color",
          "filePath": "/Users/victorneves/_code/EKP-Frontend/styleDictionary/tokens/enbw/color/type.json",
          "isSource": true,
          "original": {
            "value": "{col.base.sunnyellow.50.value}",
            "type": "color"
          },
          "name": "col-type-link-visited",
          "attributes": {},
          "path": [
            "col",
            "type",
            "link",
            "visited"
          ]
        },
        "underline": {
          "value": "#FFC736",
          "type": "color",
          "filePath": "/Users/victorneves/_code/EKP-Frontend/styleDictionary/tokens/enbw/color/type.json",
          "isSource": true,
          "original": {
            "value": "{col.base.sunnyellow.50.value}",
            "type": "color"
          },
          "name": "col-type-link-underline",
          "attributes": {},
          "path": [
            "col",
            "type",
            "link",
            "underline"
          ]
        },
        "outline": {
          "value": "#FFC736",
          "type": "color",
          "filePath": "/Users/victorneves/_code/EKP-Frontend/styleDictionary/tokens/enbw/color/type.json",
          "isSource": true,
          "original": {
            "value": "{col.base.sunnyellow.50.value}",
            "type": "color"
          },
          "name": "col-type-link-outline",
          "attributes": {},
          "path": [
            "col",
            "type",
            "link",
            "outline"
          ]
        }
      }
    }
  },
  "shadow": {
    "button": {
      "type": "shadow",
      "value": "black 0 0 8px",
      "filePath": "/Users/victorneves/_code/EKP-Frontend/styleDictionary/tokens/enbw/shadows/shadows.json",
      "isSource": true,
      "original": {
        "type": "shadow",
        "value": "{col.base.black.value} 0 0 8px"
      },
      "name": "shadow-button",
      "attributes": {},
      "path": [
        "shadow",
        "button"
      ]
    }
  },
  "borderRadius": {
    "s": {
      "value": "8px",
      "type": "borderRadius",
      "filePath": "/Users/victorneves/_code/EKP-Frontend/styleDictionary/tokens/enbw/sizes/border-radius.json",
      "isSource": true,
      "original": {
        "value": "8px",
        "type": "borderRadius"
      },
      "name": "border-radius-s",
      "attributes": {},
      "path": [
        "borderRadius",
        "s"
      ]
    },
    "m": {
      "value": "10px",
      "type": "borderRadius",
      "filePath": "/Users/victorneves/_code/EKP-Frontend/styleDictionary/tokens/enbw/sizes/border-radius.json",
      "isSource": true,
      "original": {
        "value": "10px",
        "type": "borderRadius"
      },
      "name": "border-radius-m",
      "attributes": {},
      "path": [
        "borderRadius",
        "m"
      ]
    },
    "l": {
      "value": "12px",
      "type": "borderRadius",
      "filePath": "/Users/victorneves/_code/EKP-Frontend/styleDictionary/tokens/enbw/sizes/border-radius.json",
      "isSource": true,
      "original": {
        "value": "12px",
        "type": "borderRadius"
      },
      "name": "border-radius-l",
      "attributes": {},
      "path": [
        "borderRadius",
        "l"
      ]
    }
  },
  "Sizes": {
    "breakpoints": {
      "s": {
        "value": "320px",
        "type": "sizing",
        "filePath": "/Users/victorneves/_code/EKP-Frontend/styleDictionary/tokens/enbw/sizes/sizes.js",
        "isSource": true,
        "original": {
          "value": "320px",
          "type": "sizing"
        },
        "name": "sizes-breakpoints-s",
        "attributes": {},
        "path": [
          "Sizes",
          "breakpoints",
          "s"
        ]
      },
      "m": {
        "value": "760px",
        "type": "sizing",
        "filePath": "/Users/victorneves/_code/EKP-Frontend/styleDictionary/tokens/enbw/sizes/sizes.js",
        "isSource": true,
        "original": {
          "value": "760px",
          "type": "sizing"
        },
        "name": "sizes-breakpoints-m",
        "attributes": {},
        "path": [
          "Sizes",
          "breakpoints",
          "m"
        ]
      },
      "l": {
        "value": "900px",
        "type": "sizing",
        "filePath": "/Users/victorneves/_code/EKP-Frontend/styleDictionary/tokens/enbw/sizes/sizes.js",
        "isSource": true,
        "original": {
          "value": "900px",
          "type": "sizing"
        },
        "name": "sizes-breakpoints-l",
        "attributes": {},
        "path": [
          "Sizes",
          "breakpoints",
          "l"
        ]
      },
      "xl": {
        "value": "1376px",
        "type": "sizing",
        "filePath": "/Users/victorneves/_code/EKP-Frontend/styleDictionary/tokens/enbw/sizes/sizes.js",
        "isSource": true,
        "original": {
          "value": "1376px",
          "type": "sizing"
        },
        "name": "sizes-breakpoints-xl",
        "attributes": {},
        "path": [
          "Sizes",
          "breakpoints",
          "xl"
        ]
      }
    },
    "spacings": {
      "increment": {
        "value": 5,
        "type": "sizing",
        "filePath": "/Users/victorneves/_code/EKP-Frontend/styleDictionary/tokens/enbw/sizes/sizes.js",
        "isSource": true,
        "original": {
          "value": 5,
          "type": "sizing"
        },
        "name": "sizes-spacings-increment",
        "attributes": {},
        "path": [
          "Sizes",
          "spacings",
          "increment"
        ]
      },
      "s": {
        "xxs": {
          "value": "5px",
          "type": "sizing",
          "filePath": "/Users/victorneves/_code/EKP-Frontend/styleDictionary/tokens/enbw/sizes/sizes.js",
          "isSource": true,
          "original": {
            "value": "5px",
            "type": "sizing"
          },
          "name": "sizes-spacings-s-xxs",
          "attributes": {},
          "path": [
            "Sizes",
            "spacings",
            "s",
            "xxs"
          ]
        },
        "xs": {
          "value": "10px",
          "type": "sizing",
          "filePath": "/Users/victorneves/_code/EKP-Frontend/styleDictionary/tokens/enbw/sizes/sizes.js",
          "isSource": true,
          "original": {
            "value": "10px",
            "type": "sizing"
          },
          "name": "sizes-spacings-s-xs",
          "attributes": {},
          "path": [
            "Sizes",
            "spacings",
            "s",
            "xs"
          ]
        },
        "s": {
          "value": "15px",
          "type": "sizing",
          "filePath": "/Users/victorneves/_code/EKP-Frontend/styleDictionary/tokens/enbw/sizes/sizes.js",
          "isSource": true,
          "original": {
            "value": "15px",
            "type": "sizing"
          },
          "name": "sizes-spacings-s-s",
          "attributes": {},
          "path": [
            "Sizes",
            "spacings",
            "s",
            "s"
          ]
        },
        "m": {
          "value": "20px",
          "type": "sizing",
          "filePath": "/Users/victorneves/_code/EKP-Frontend/styleDictionary/tokens/enbw/sizes/sizes.js",
          "isSource": true,
          "original": {
            "value": "20px",
            "type": "sizing"
          },
          "name": "sizes-spacings-s-m",
          "attributes": {},
          "path": [
            "Sizes",
            "spacings",
            "s",
            "m"
          ]
        },
        "l": {
          "value": "25px",
          "type": "sizing",
          "filePath": "/Users/victorneves/_code/EKP-Frontend/styleDictionary/tokens/enbw/sizes/sizes.js",
          "isSource": true,
          "original": {
            "value": "25px",
            "type": "sizing"
          },
          "name": "sizes-spacings-s-l",
          "attributes": {},
          "path": [
            "Sizes",
            "spacings",
            "s",
            "l"
          ]
        },
        "xl": {
          "value": "30px",
          "type": "sizing",
          "filePath": "/Users/victorneves/_code/EKP-Frontend/styleDictionary/tokens/enbw/sizes/sizes.js",
          "isSource": true,
          "original": {
            "value": "30px",
            "type": "sizing"
          },
          "name": "sizes-spacings-s-xl",
          "attributes": {},
          "path": [
            "Sizes",
            "spacings",
            "s",
            "xl"
          ]
        },
        "xxl": {
          "value": "35px",
          "type": "sizing",
          "filePath": "/Users/victorneves/_code/EKP-Frontend/styleDictionary/tokens/enbw/sizes/sizes.js",
          "isSource": true,
          "original": {
            "value": "35px",
            "type": "sizing"
          },
          "name": "sizes-spacings-s-xxl",
          "attributes": {},
          "path": [
            "Sizes",
            "spacings",
            "s",
            "xxl"
          ]
        }
      },
      "l": {
        "xxs": {
          "value": "15px",
          "type": "sizing",
          "filePath": "/Users/victorneves/_code/EKP-Frontend/styleDictionary/tokens/enbw/sizes/sizes.js",
          "isSource": true,
          "original": {
            "value": "15px",
            "type": "sizing"
          },
          "name": "sizes-spacings-l-xxs",
          "attributes": {},
          "path": [
            "Sizes",
            "spacings",
            "l",
            "xxs"
          ]
        },
        "xs": {
          "value": "20px",
          "type": "sizing",
          "filePath": "/Users/victorneves/_code/EKP-Frontend/styleDictionary/tokens/enbw/sizes/sizes.js",
          "isSource": true,
          "original": {
            "value": "20px",
            "type": "sizing"
          },
          "name": "sizes-spacings-l-xs",
          "attributes": {},
          "path": [
            "Sizes",
            "spacings",
            "l",
            "xs"
          ]
        },
        "s": {
          "value": "25px",
          "type": "sizing",
          "filePath": "/Users/victorneves/_code/EKP-Frontend/styleDictionary/tokens/enbw/sizes/sizes.js",
          "isSource": true,
          "original": {
            "value": "25px",
            "type": "sizing"
          },
          "name": "sizes-spacings-l-s",
          "attributes": {},
          "path": [
            "Sizes",
            "spacings",
            "l",
            "s"
          ]
        },
        "m": {
          "value": "30px",
          "type": "sizing",
          "filePath": "/Users/victorneves/_code/EKP-Frontend/styleDictionary/tokens/enbw/sizes/sizes.js",
          "isSource": true,
          "original": {
            "value": "30px",
            "type": "sizing"
          },
          "name": "sizes-spacings-l-m",
          "attributes": {},
          "path": [
            "Sizes",
            "spacings",
            "l",
            "m"
          ]
        },
        "l": {
          "value": "35px",
          "type": "sizing",
          "filePath": "/Users/victorneves/_code/EKP-Frontend/styleDictionary/tokens/enbw/sizes/sizes.js",
          "isSource": true,
          "original": {
            "value": "35px",
            "type": "sizing"
          },
          "name": "sizes-spacings-l-l",
          "attributes": {},
          "path": [
            "Sizes",
            "spacings",
            "l",
            "l"
          ]
        },
        "xl": {
          "value": "40px",
          "type": "sizing",
          "filePath": "/Users/victorneves/_code/EKP-Frontend/styleDictionary/tokens/enbw/sizes/sizes.js",
          "isSource": true,
          "original": {
            "value": "40px",
            "type": "sizing"
          },
          "name": "sizes-spacings-l-xl",
          "attributes": {},
          "path": [
            "Sizes",
            "spacings",
            "l",
            "xl"
          ]
        },
        "xxl": {
          "value": "45px",
          "type": "sizing",
          "filePath": "/Users/victorneves/_code/EKP-Frontend/styleDictionary/tokens/enbw/sizes/sizes.js",
          "isSource": true,
          "original": {
            "value": "45px",
            "type": "sizing"
          },
          "name": "sizes-spacings-l-xxl",
          "attributes": {},
          "path": [
            "Sizes",
            "spacings",
            "l",
            "xxl"
          ]
        }
      }
    },
    "page": {
      "min": {
        "value": "320px",
        "type": "sizing",
        "filePath": "/Users/victorneves/_code/EKP-Frontend/styleDictionary/tokens/enbw/sizes/sizes.js",
        "isSource": true,
        "original": {
          "value": "320px",
          "type": "sizing"
        },
        "name": "sizes-page-min",
        "attributes": {},
        "path": [
          "Sizes",
          "page",
          "min"
        ]
      },
      "margin-hor": {
        "value": "20px",
        "type": "sizing",
        "filePath": "/Users/victorneves/_code/EKP-Frontend/styleDictionary/tokens/enbw/sizes/sizes.js",
        "isSource": true,
        "original": {
          "value": "{Sizes.spacings.s.m.value}",
          "type": "sizing"
        },
        "name": "sizes-page-margin-hor",
        "attributes": {},
        "path": [
          "Sizes",
          "page",
          "margin-hor"
        ]
      }
    },
    "content": {
      "min": {
        "value": "280px",
        "type": "sizing",
        "filePath": "/Users/victorneves/_code/EKP-Frontend/styleDictionary/tokens/enbw/sizes/sizes.js",
        "isSource": true,
        "original": {
          "value": "280px",
          "type": "sizing"
        },
        "name": "sizes-content-min",
        "attributes": {},
        "path": [
          "Sizes",
          "content",
          "min"
        ]
      },
      "max": {
        "value": "1092px",
        "type": "sizing",
        "filePath": "/Users/victorneves/_code/EKP-Frontend/styleDictionary/tokens/enbw/sizes/sizes.js",
        "isSource": true,
        "original": {
          "value": "1092px",
          "type": "sizing"
        },
        "name": "sizes-content-max",
        "attributes": {},
        "path": [
          "Sizes",
          "content",
          "max"
        ]
      }
    }
  },
  "font": {
    "family": {
      "ffmark": {
        "value": "ffMark, sans-serif",
        "type": "fontFamily",
        "filePath": "/Users/victorneves/_code/EKP-Frontend/styleDictionary/tokens/enbw/typography/typography.js",
        "isSource": true,
        "original": {
          "value": "ffMark, sans-serif",
          "type": "fontFamily"
        },
        "name": "font-family-ffmark",
        "attributes": {},
        "path": [
          "font",
          "family",
          "ffmark"
        ]
      },
      "enbwdin": {
        "value": "EnbwDin, sans-serif",
        "type": "fontFamily",
        "filePath": "/Users/victorneves/_code/EKP-Frontend/styleDictionary/tokens/enbw/typography/typography.js",
        "isSource": true,
        "original": {
          "value": "EnbwDin, sans-serif",
          "type": "fontFamily"
        },
        "name": "font-family-enbwdin",
        "attributes": {},
        "path": [
          "font",
          "family",
          "enbwdin"
        ]
      }
    },
    "weight": {
      "lightWeight": {
        "value": 100,
        "type": "fontWeight",
        "filePath": "/Users/victorneves/_code/EKP-Frontend/styleDictionary/tokens/enbw/typography/typography.js",
        "isSource": true,
        "original": {
          "value": 100,
          "type": "fontWeight"
        },
        "name": "font-weight-light-weight",
        "attributes": {},
        "path": [
          "font",
          "weight",
          "lightWeight"
        ]
      },
      "regWeight": {
        "value": 300,
        "type": "fontWeight",
        "filePath": "/Users/victorneves/_code/EKP-Frontend/styleDictionary/tokens/enbw/typography/typography.js",
        "isSource": true,
        "original": {
          "value": 300,
          "type": "fontWeight"
        },
        "name": "font-weight-reg-weight",
        "attributes": {},
        "path": [
          "font",
          "weight",
          "regWeight"
        ]
      },
      "mediumWeight": {
        "value": 500,
        "type": "fontWeight",
        "filePath": "/Users/victorneves/_code/EKP-Frontend/styleDictionary/tokens/enbw/typography/typography.js",
        "isSource": true,
        "original": {
          "value": 500,
          "type": "fontWeight"
        },
        "name": "font-weight-medium-weight",
        "attributes": {},
        "path": [
          "font",
          "weight",
          "mediumWeight"
        ]
      },
      "semiBoldWeight": {
        "value": 600,
        "type": "fontWeight",
        "filePath": "/Users/victorneves/_code/EKP-Frontend/styleDictionary/tokens/enbw/typography/typography.js",
        "isSource": true,
        "original": {
          "value": 600,
          "type": "fontWeight"
        },
        "name": "font-weight-semi-bold-weight",
        "attributes": {},
        "path": [
          "font",
          "weight",
          "semiBoldWeight"
        ]
      },
      "boldWeight": {
        "value": 700,
        "type": "fontWeight",
        "filePath": "/Users/victorneves/_code/EKP-Frontend/styleDictionary/tokens/enbw/typography/typography.js",
        "isSource": true,
        "original": {
          "value": 700,
          "type": "fontWeight"
        },
        "name": "font-weight-bold-weight",
        "attributes": {},
        "path": [
          "font",
          "weight",
          "boldWeight"
        ]
      }
    },
    "size": {
      "xxxl": {
        "value": "36px",
        "type": "fontSize",
        "filePath": "/Users/victorneves/_code/EKP-Frontend/styleDictionary/tokens/enbw/typography/typography.js",
        "isSource": true,
        "original": {
          "value": "36px",
          "type": "fontSize"
        },
        "name": "font-size-xxxl",
        "attributes": {},
        "path": [
          "font",
          "size",
          "xxxl"
        ]
      },
      "xxl": {
        "value": "30px",
        "type": "fontSize",
        "filePath": "/Users/victorneves/_code/EKP-Frontend/styleDictionary/tokens/enbw/typography/typography.js",
        "isSource": true,
        "original": {
          "value": "30px",
          "type": "fontSize"
        },
        "name": "font-size-xxl",
        "attributes": {},
        "path": [
          "font",
          "size",
          "xxl"
        ]
      },
      "xl": {
        "value": "24px",
        "type": "fontSize",
        "filePath": "/Users/victorneves/_code/EKP-Frontend/styleDictionary/tokens/enbw/typography/typography.js",
        "isSource": true,
        "original": {
          "value": "24px",
          "type": "fontSize"
        },
        "name": "font-size-xl",
        "attributes": {},
        "path": [
          "font",
          "size",
          "xl"
        ]
      },
      "l": {
        "value": "20px",
        "type": "fontSize",
        "filePath": "/Users/victorneves/_code/EKP-Frontend/styleDictionary/tokens/enbw/typography/typography.js",
        "isSource": true,
        "original": {
          "value": "20px",
          "type": "fontSize"
        },
        "name": "font-size-l",
        "attributes": {},
        "path": [
          "font",
          "size",
          "l"
        ]
      },
      "xm": {
        "value": "18px",
        "type": "fontSize",
        "filePath": "/Users/victorneves/_code/EKP-Frontend/styleDictionary/tokens/enbw/typography/typography.js",
        "isSource": true,
        "original": {
          "value": "18px",
          "type": "fontSize"
        },
        "name": "font-size-xm",
        "attributes": {},
        "path": [
          "font",
          "size",
          "xm"
        ]
      },
      "m": {
        "value": "16px",
        "type": "fontSize",
        "filePath": "/Users/victorneves/_code/EKP-Frontend/styleDictionary/tokens/enbw/typography/typography.js",
        "isSource": true,
        "original": {
          "value": "16px",
          "type": "fontSize"
        },
        "name": "font-size-m",
        "attributes": {},
        "path": [
          "font",
          "size",
          "m"
        ]
      },
      "s": {
        "value": "14px",
        "type": "fontSize",
        "filePath": "/Users/victorneves/_code/EKP-Frontend/styleDictionary/tokens/enbw/typography/typography.js",
        "isSource": true,
        "original": {
          "value": "14px",
          "type": "fontSize"
        },
        "name": "font-size-s",
        "attributes": {},
        "path": [
          "font",
          "size",
          "s"
        ]
      },
      "xs": {
        "value": "12px",
        "type": "fontSize",
        "filePath": "/Users/victorneves/_code/EKP-Frontend/styleDictionary/tokens/enbw/typography/typography.js",
        "isSource": true,
        "original": {
          "value": "12px",
          "type": "fontSize"
        },
        "name": "font-size-xs",
        "attributes": {},
        "path": [
          "font",
          "size",
          "xs"
        ]
      }
    },
    "lh": {
      "identifier": {
        "value": 1.25,
        "type": "lineHeight",
        "filePath": "/Users/victorneves/_code/EKP-Frontend/styleDictionary/tokens/enbw/typography/typography.js",
        "isSource": true,
        "original": {
          "value": 1.25,
          "type": "lineHeight"
        },
        "name": "font-lh-identifier",
        "attributes": {},
        "path": [
          "font",
          "lh",
          "identifier"
        ]
      },
      "heading": {
        "value": 1.25,
        "type": "lineHeight",
        "filePath": "/Users/victorneves/_code/EKP-Frontend/styleDictionary/tokens/enbw/typography/typography.js",
        "isSource": true,
        "original": {
          "value": 1.25,
          "type": "lineHeight"
        },
        "name": "font-lh-heading",
        "attributes": {},
        "path": [
          "font",
          "lh",
          "heading"
        ]
      },
      "subheading": {
        "value": 1.25,
        "type": "lineHeight",
        "filePath": "/Users/victorneves/_code/EKP-Frontend/styleDictionary/tokens/enbw/typography/typography.js",
        "isSource": true,
        "original": {
          "value": 1.25,
          "type": "lineHeight"
        },
        "name": "font-lh-subheading",
        "attributes": {},
        "path": [
          "font",
          "lh",
          "subheading"
        ]
      },
      "copy": {
        "value": 1.5,
        "type": "lineHeight",
        "filePath": "/Users/victorneves/_code/EKP-Frontend/styleDictionary/tokens/enbw/typography/typography.js",
        "isSource": true,
        "original": {
          "value": 1.5,
          "type": "lineHeight"
        },
        "name": "font-lh-copy",
        "attributes": {},
        "path": [
          "font",
          "lh",
          "copy"
        ]
      },
      "caption": {
        "value": 1.5,
        "type": "lineHeight",
        "filePath": "/Users/victorneves/_code/EKP-Frontend/styleDictionary/tokens/enbw/typography/typography.js",
        "isSource": true,
        "original": {
          "value": 1.5,
          "type": "lineHeight"
        },
        "name": "font-lh-caption",
        "attributes": {},
        "path": [
          "font",
          "lh",
          "caption"
        ]
      }
    }
  }
}